{
  "price-list-flyer.jpg": {
    "title": "Price List Flyer"
  },
  "script-logo-sign.jpg": {
    "title": "Script Logo Sign"
  },
  "round-logo-emblem.jpg": {
    "title": "Round Logo Emblem"
  },
  "banana-pudding-desserts.jpg": {
    "title": "Pumpkin Pie Desserts"
  },
  "minnie-mouse-pastel-cake.jpg": {
    "title": "Minnie Mouse Pastel Cake"
  },
  "blue-snowflake-winter-cake.jpg": {
    "title": "Blue Snowflake Winter Cake"
  },
  "baseball-cake.jpg": {
    "title": "Baseball Cake"
  },
  "mm-candy-drip-cake.jpg": {
    "title": "M&M Candy Drip Cake"
  },
  "pink-pearl-celebration-cake.jpg": {
    "title": "Pink Pearl Celebration Cake"
  },
  "white-floral-sheet-cake.jpg": {
    "title": "White Floral Sheet Cake"
  },
  "pastel-swirl-cupcakes.jpg": {
    "title": "Pastel Swirl Cupcakes"
  },
  "teddy-bear-baby-shower-cake.jpg": {
    "title": "Teddy Bear Baby Shower Cake"
  },
  "silver-cupcake-tray.jpg": {
    "title": "Silver Cupcake Tray"
  },
  "white-cupcake-tray.jpg": {
    "title": "White Cupcake Tray"
  },
  "emoji-cupcake-tray.jpg": {
    "title": "Emoji Cupcake Tray"
  },
  "photo-collage-celebration-cake.jpg": {
    "title": "Photo Collage Celebration Cake"
  },
  "horror-movie-themed-cake.jpg": {
    "title": "Horror Movie Themed Cake"
  },
  "june-availability-calendar.jpg": {
    "title": "June Availability Calendar"
  },
  "cupcake-logo-card.jpg": {
    "title": "Cupcake Logo Card"
  },
  "logo-card-clean.jpg": {
    "title": "Logo Card"
  },
  "orange-crown-birthday-cake.jpg": {
    "title": "Orange Crown Birthday Cake"
  },
  "ladybug-heart-sheet-cake.jpg": {
    "title": "Ladybug Heart Sheet Cake"
  },
  "spiderweb-halloween-cake.jpg": {
    "title": "Spiderweb Halloween Cake"
  },
  "purple-rosette-cake.jpg": {
    "title": "Purple Rosette Cake"
  },
  "welcome-scroll-cake.jpg": {
    "title": "Welcome Scroll Cake"
  },
  "anime-portrait-cake.jpg": {
    "title": "Anime Portrait Cake"
  },
  "elmo-mini-cakes-and-cupcakes.jpg": {
    "title": "Elmo Mini Cakes and Cupcakes"
  },
  "animal-face-cupcakes.jpg": {
    "title": "Animal Face Cupcakes"
  },
  "pink-monster-cake.jpg": {
    "title": "Pink Monster Cake"
  },
  "blue-beach-cake.jpg": {
    "title": "Blue Beach Cake"
  },
  "paw-patrol-sheet-cake.jpg": {
    "title": "Paw Patrol Sheet Cake"
  },
  "parrot-birthday-cake.jpg": {
    "title": "Parrot Birthday Cake"
  },
  "ocean-beach-scene-cake.jpg": {
    "title": "Ocean Beach Scene Cake"
  },
  "chocolate-cream-cheesecake.jpg": {
    "title": "Chocolate Cream Cheesecake"
  },
  "military-appreciation-cake.jpg": {
    "title": "Military Appreciation Cake"
  },
  "yellow-brick-road-cake.jpg": {
    "title": "Yellow Brick Road Cake"
  },
  "welder-tool-cake.jpg": {
    "title": "Welder Tool Cake"
  },
  "dessert-stand-display.jpg": {
    "title": "Dessert Stand Display"
  },
  "batman-city-cake-and-cupcakes.jpg": {
    "title": "Batman City Cake and Cupcakes"
  },
  "pokeball-mini-cakes.jpg": {
    "title": "Pokeball Mini Cakes"
  },
  "steelers-football-cake.jpg": {
    "title": "Steelers Football Cake"
  },
  "guitar-birthday-cake.jpg": {
    "title": "Guitar Birthday Cake"
  },
  "dog-face-cake.jpg": {
    "title": "Dog Face Cake"
  },
  "football-cupcakes.jpg": {
    "title": "Football Cupcakes"
  },
  "blue-cat-yarn-cake.jpg": {
    "title": "Blue Cat Yarn Cake"
  }
}
